mkimgproxy/__init__.py
mkimgproxy-0.4.dist-info/LICENSE
mkimgproxy-0.4.dist-info/WHEEL
mkimgproxy-0.4.dist-info/METADATA
mkimgproxy-0.4.dist-info/RECORD
