Metadata-Version: 2.1
Name: mkimgproxy
Version: 0.4
Summary: Generates URL for imgproxy image processing server
Home-page: https://github.com/maxim75/mkimgproxy
License: MIT
Keywords: imgproxy image
Author: Maksym Kozlenko
Author-email: max@kozlenko.info
Classifier: License :: OSI Approved :: MIT License
